{
  "users": [
    {
      "name": "admin",
      "password": "admin123",
      "tags": "administrator"
    },
    {
      "name": "notification_users",
      "password": "n2o3t4i5f6i",
      "tags": ""
    },
    {
      "name": "auth_users",
      "password": "a1u2t3h4",
      "tags": ""
    }
  ],
  "vhosts": [
    {
      "name": "/notification"
    },
    {
      "name": "/auth"
    }
  ],
  "permissions": [
    {
      "user": "admin",
      "vhost": "/",
      "configure": ".*",
      "write": ".*",
      "read": ".*"
    },
    {
      "user": "notification_users",
      "vhost": "/notification",
      "configurer": ".*",
      "write": "",
      "read": ".*"
    },
    {
      "user": "auth_users",
      "vhost": "/auth",
      "configurer": "",
      "write": ".*",
      "read": ""
    }
  ]
}